dpk_doc_chunk/__init__.py
dpk_doc_chunk/chunkers.py
dpk_doc_chunk/local.py
dpk_doc_chunk/local_python.py
dpk_doc_chunk/transform.py
dpk_doc_chunk/transform_python.py
dpk_doc_chunk/ray/__init__.py
dpk_doc_chunk/ray/local.py
dpk_doc_chunk/ray/s3.py
dpk_doc_chunk/ray/transform.py
dpk_doc_id/__init__.py
dpk_doc_id/local.py
dpk_doc_id/local_python.py
dpk_doc_id/transform.py
dpk_doc_id/transform_python.py
dpk_doc_id/ray/__init__.py
dpk_doc_id/ray/local.py
dpk_doc_id/ray/s3.py
dpk_doc_id/ray/transform.py
dpk_doc_id/spark/__init__.py
dpk_doc_id/spark/local.py
dpk_doc_id/spark/transform.py
dpk_doc_quality/__init__.py
dpk_doc_quality/cc_net_prepro.py
dpk_doc_quality/doc_Gopher_statistics.py
dpk_doc_quality/doc_c4_statistics.py
dpk_doc_quality/local.py
dpk_doc_quality/local_python.py
dpk_doc_quality/transform.py
dpk_doc_quality/transform_python.py
dpk_doc_quality/utils.py
dpk_doc_quality/ldnoobw/de
dpk_doc_quality/ldnoobw/en
dpk_doc_quality/ldnoobw/es
dpk_doc_quality/ldnoobw/fr
dpk_doc_quality/ldnoobw/ja
dpk_doc_quality/ldnoobw/pt
dpk_doc_quality/ray/__init__.py
dpk_doc_quality/ray/local.py
dpk_doc_quality/ray/s3.py
dpk_doc_quality/ray/transform.py
dpk_hap/__init__.py
dpk_hap/local.py
dpk_hap/local_python.py
dpk_hap/transform.py
dpk_hap/transform_python.py
dpk_hap/ray/__init__.py
dpk_hap/ray/local.py
dpk_hap/ray/s3.py
dpk_hap/ray/transform.py
dpk_html2parquet/__init__.py
dpk_html2parquet/local.py
dpk_html2parquet/local_python.py
dpk_html2parquet/transform.py
dpk_html2parquet/transform_python.py
dpk_html2parquet/ray/__init__.py
dpk_html2parquet/ray/local_ray.py
dpk_html2parquet/ray/s3_ray.py
dpk_html2parquet/ray/transform.py
dpk_lang_id/lang_models.py
dpk_lang_id/local.py
dpk_lang_id/local_python.py
dpk_lang_id/nlp.py
dpk_lang_id/transform.py
dpk_lang_id/transform_python.py
dpk_lang_id/ray/local.py
dpk_lang_id/ray/s3.py
dpk_lang_id/ray/transform.py
dpk_pdf2parquet/.dockerignore
dpk_pdf2parquet/.gitignore
dpk_pdf2parquet/__init__.py
dpk_pdf2parquet/local.py
data_prep_toolkit_lang-1.0.0a0.dist-info/METADATA
data_prep_toolkit_lang-1.0.0a0.dist-info/WHEEL
data_prep_toolkit_lang-1.0.0a0.dist-info/top_level.txt
data_prep_toolkit_lang-1.0.0a0.dist-info/RECORD
