Metadata-Version: 2.1
Name: data_prep_toolkit_lang
Version: 1.0.0a0
Summary: Data Preparation Toolkit Transforms using Ray
Author-email: Maroun Touma <touma@us.ibm.com>
License: Apache-2.0
Keywords: transforms,data preprocessing,data preparation,llm,generative,ai,fine-tuning,llmapps
Requires-Python: <3.13,>=3.10
Requires-Dist: data-prep-toolkit>=0.2.3.dev0
Provides-Extra: dev
Requires-Dist: twine; extra == "dev"
Requires-Dist: pytest>=7.3.2; extra == "dev"
Requires-Dist: pytest-dotenv>=0.5.2; extra == "dev"
Requires-Dist: pytest-env>=1.0.0; extra == "dev"
Requires-Dist: pre-commit>=3.3.2; extra == "dev"
Requires-Dist: pytest-cov>=4.1.0; extra == "dev"
Requires-Dist: pytest-mock>=3.10.0; extra == "dev"
Requires-Dist: moto==5.0.5; extra == "dev"
Requires-Dist: markupsafe==2.0.1; extra == "dev"
Provides-Extra: ray
Requires-Dist: data-prep-toolkit[ray]>=0.2.3.dev0; extra == "ray"
Requires-Dist: networkx==3.3; extra == "ray"
Requires-Dist: colorlog==6.8.2; extra == "ray"
Requires-Dist: func-timeout==4.3.5; extra == "ray"
Requires-Dist: emerge-viz==2.0.0; extra == "ray"
Provides-Extra: all
Requires-Dist: data-prep-toolkit>=0.2.3.dev0; extra == "all"
Requires-Dist: data-prep-toolkit>=0.2.3.dev0; extra == "all"
Requires-Dist: docling-core==2.3.0; extra == "all"
Requires-Dist: pydantic<2.10.0,>=2.0.0; extra == "all"
Requires-Dist: llama-index-core<0.12.0,>=0.11.22; extra == "all"
Requires-Dist: data-prep-toolkit>=0.2.3.dev0; extra == "all"
Requires-Dist: fasttext==0.9.2; extra == "all"
Requires-Dist: langcodes==3.3.0; extra == "all"
Requires-Dist: huggingface-hub<1.0.0,>=0.21.4; extra == "all"
Requires-Dist: numpy==1.26.4; extra == "all"
Requires-Dist: data-prep-toolkit>=0.2.3.dev0; extra == "all"
Requires-Dist: sentence-transformers==3.0.1; extra == "all"
Requires-Dist: docling-core==2.3.0; extra == "all"
Requires-Dist: docling-ibm-models==2.0.3; extra == "all"
Requires-Dist: deepsearch-glm==0.26.1; extra == "all"
Requires-Dist: docling==2.3.1; extra == "all"
Requires-Dist: filetype<2.0.0,>=1.2.0; extra == "all"
Requires-Dist: data-prep-toolkit>=0.2.3.dev0; extra == "all"
Requires-Dist: data-prep-toolkit>=0.2.3.dev0; extra == "all"
Requires-Dist: mmh3>=4.1.0; extra == "all"
Requires-Dist: xxhash==3.4.1; extra == "all"
Requires-Dist: data-prep-toolkit>=0.2.3.dev0; extra == "all"
Requires-Dist: nltk==3.9.1; extra == "all"
Requires-Dist: transformers==4.38.2; extra == "all"
Requires-Dist: torch<=2.4.1,>=2.2.2; extra == "all"
Requires-Dist: pandas==2.2.2; extra == "all"
Requires-Dist: data-prep-toolkit>=0.2.3.dev0; extra == "all"
Requires-Dist: transformers==4.38.2; extra == "all"
Requires-Dist: data-prep-toolkit>=0.2.3.dev0; extra == "all"
Requires-Dist: data_prep_connector>=0.2.3; extra == "all"
Provides-Extra: doc-chunk
Requires-Dist: data-prep-toolkit>=0.2.3.dev0; extra == "doc-chunk"
Requires-Dist: docling-core==2.3.0; extra == "doc-chunk"
Requires-Dist: pydantic<2.10.0,>=2.0.0; extra == "doc-chunk"
Requires-Dist: llama-index-core<0.12.0,>=0.11.22; extra == "doc-chunk"
Provides-Extra: doc-quality
Requires-Dist: data-prep-toolkit>=0.2.3.dev0; extra == "doc-quality"
Provides-Extra: html2parquet
Requires-Dist: data-prep-toolkit>=0.2.3.dev0; extra == "html2parquet"
Requires-Dist: trafilatura==1.12.0; extra == "html2parquet"
Provides-Extra: lang-id
Requires-Dist: data-prep-toolkit>=0.2.3.dev0; extra == "lang-id"
Requires-Dist: fasttext==0.9.2; extra == "lang-id"
Requires-Dist: langcodes==3.3.0; extra == "lang-id"
Requires-Dist: huggingface-hub<1.0.0,>=0.21.4; extra == "lang-id"
Requires-Dist: numpy==1.26.4; extra == "lang-id"
Provides-Extra: pdf2parquet
Requires-Dist: docling-core==2.3.0; extra == "pdf2parquet"
Requires-Dist: docling-ibm-models==2.0.3; extra == "pdf2parquet"
Requires-Dist: deepsearch-glm==0.26.1; extra == "pdf2parquet"
Requires-Dist: docling==2.3.1; extra == "pdf2parquet"
Requires-Dist: filetype<2.0.0,>=1.2.0; extra == "pdf2parquet"
Provides-Extra: text-encoder
Requires-Dist: data-prep-toolkit>=0.2.3.dev0; extra == "text-encoder"
Requires-Dist: sentence-transformers==3.0.1; extra == "text-encoder"
Provides-Extra: doc-id
Requires-Dist: data-prep-toolkit>=0.2.3.dev0; extra == "doc-id"
Provides-Extra: ededup
Requires-Dist: data-prep-toolkit>=0.2.3.dev0; extra == "ededup"
Requires-Dist: mmh3>=4.1.0; extra == "ededup"
Requires-Dist: xxhash==3.4.1; extra == "ededup"
Provides-Extra: hap
Requires-Dist: data-prep-toolkit>=0.2.3.dev0; extra == "hap"
Requires-Dist: nltk==3.9.1; extra == "hap"
Requires-Dist: transformers==4.38.2; extra == "hap"
Requires-Dist: torch<=2.4.1,>=2.2.2; extra == "hap"
Requires-Dist: pandas==2.2.2; extra == "hap"
Provides-Extra: tokenization
Requires-Dist: data-prep-toolkit>=0.2.3.dev0; extra == "tokenization"
Requires-Dist: transformers==4.38.2; extra == "tokenization"
Provides-Extra: web2parquet
Requires-Dist: data-prep-toolkit>=0.2.3.dev0; extra == "web2parquet"
Requires-Dist: data_prep_connector>=0.2.3; extra == "web2parquet"
